burdenr/__init__.py
burdenr/cli.py
burdenr/tools/Grantham_Scores.json
burdenr/tools/callrisk.py
burdenr/tools/handle_data.py
burdenr/tools/handle_data_vcf.py
burdenr-0.1.1.dist-info/METADATA
burdenr-0.1.1.dist-info/WHEEL
burdenr-0.1.1.dist-info/entry_points.txt
burdenr-0.1.1.dist-info/top_level.txt
burdenr-0.1.1.dist-info/RECORD
